CHANGES.rst
LICENSE
MANIFEST.in
README.rst
setup.py
test_checkout.py
checkout/__init__.py
checkout.egg-info/PKG-INFO
checkout.egg-info/SOURCES.txt
checkout.egg-info/dependency_links.txt
checkout.egg-info/not-zip-safe
checkout.egg-info/requires.txt
checkout.egg-info/top_level.txt