Metadata-Version: 1.1
Name: checkout
Version: 0.2.0
Summary: Python wrapper for the Checkout Finland API.
Home-page: http://github.com/tuomasb/python-checkout
Author: Tuomas Blomqvist, Janne Vanhala
Author-email: tuomas.blomqvist@gmail.com, janne@fastmonkeys.com
License: BSD
Platform: any
Classifier: Development Status :: 4 - Beta
Classifier: Intended Audience :: Developers
Classifier: License :: OSI Approved :: BSD License
Classifier: Operating System :: OS Independent
Classifier: Programming Language :: Python
Classifier: Topic :: Software Development :: Libraries :: Python Modules
